<included>
  <appender name="TCP" class="net.logstash.logback.appender.LogstashTcpSocketAppender">
    <destination>localhost:5000</destination>
    <encoder class="net.logstash.logback.encoder.LoggingEventCompositeJsonEncoder">
      <providers>
        <timestamp/>
        <version/>
        <message/>
        <loggerName/>
        <logLevel/>
        <threadName/>
        <stackTrace/>
        <arguments/>
        <mdc>
          <includeMdcKeyName>correlationId</includeMdcKeyName>
        </mdc>
        <pattern>
          <pattern>
            {
            "project": "kotlin-spring-webflux-ddd",
            "logType": "event"
            }
          </pattern>
        </pattern>
      </providers>
    </encoder>
  </appender>
</included>
